sophiegermain/__init__.py
sophiegermain/sophiegermain.py
sophiegermain-0.1.0.dist-info/LICENSE
sophiegermain-0.1.0.dist-info/METADATA
sophiegermain-0.1.0.dist-info/WHEEL
sophiegermain-0.1.0.dist-info/top_level.txt
sophiegermain-0.1.0.dist-info/RECORD
